{"namedChunkGroups":{"polyfill":{"name":"polyfill","assets":[{"name":"webpack-runtime-e52e7f4d27e91c81af93.js","size":4452},{"name":"polyfill-4eeecaf1f01bddb054ba.js","size":82641}],"filteredAssets":0,"assetsSize":87093,"filteredAuxiliaryAssets":2,"auxiliaryAssetsSize":219037},"app":{"name":"app","assets":[{"name":"webpack-runtime-e52e7f4d27e91c81af93.js","size":4452},{"name":"framework-2aa29983dbb3715690ef.js","size":128888},{"name":"app-8b15b04093186de99325.js","size":52881}],"filteredAssets":0,"assetsSize":186221,"filteredAuxiliaryAssets":3,"auxiliaryAssetsSize":551426},"component---src-pages-404-js":{"name":"component---src-pages-404-js","assets":[{"name":"styles.858d9e1bfd0c94d577d2.css","size":4216},{"name":"commons-bb84c67c674bddd9249e.js","size":17143},{"name":"component---src-pages-404-js-967ede8318a057d0dcfd.js","size":480}],"filteredAssets":0,"assetsSize":21839,"filteredAuxiliaryAssets":2,"auxiliaryAssetsSize":71213},"component---src-pages-index-js":{"name":"component---src-pages-index-js","assets":[{"name":"styles.858d9e1bfd0c94d577d2.css","size":4216},{"name":"commons-bb84c67c674bddd9249e.js","size":17143},{"name":"component---src-pages-index-js-18bf280c969509fb1ec0.js","size":2891}],"filteredAssets":0,"assetsSize":24250,"filteredAuxiliaryAssets":5,"auxiliaryAssetsSize":363606},"component---src-pages-page-2-js":{"name":"component---src-pages-page-2-js","assets":[{"name":"styles.858d9e1bfd0c94d577d2.css","size":4216},{"name":"commons-bb84c67c674bddd9249e.js","size":17143},{"name":"component---src-pages-page-2-js-894d927bbec8d66cc2ce.js","size":514}],"filteredAssets":0,"assetsSize":21873,"filteredAuxiliaryAssets":2,"auxiliaryAssetsSize":71312},"component---src-pages-using-typescript-tsx":{"name":"component---src-pages-using-typescript-tsx","assets":[{"name":"styles.858d9e1bfd0c94d577d2.css","size":4216},{"name":"commons-bb84c67c674bddd9249e.js","size":17143},{"name":"component---src-pages-using-typescript-tsx-5c68fcba212a517685e0.js","size":1325}],"filteredAssets":0,"assetsSize":22684,"filteredAuxiliaryAssets":2,"auxiliaryAssetsSize":72635}},"assetsByChunkName":{"polyfill":["webpack-runtime-e52e7f4d27e91c81af93.js","polyfill-4eeecaf1f01bddb054ba.js"],"app":["webpack-runtime-e52e7f4d27e91c81af93.js","framework-2aa29983dbb3715690ef.js","app-8b15b04093186de99325.js"],"component---src-pages-404-js":["styles.858d9e1bfd0c94d577d2.css","commons-bb84c67c674bddd9249e.js","component---src-pages-404-js-967ede8318a057d0dcfd.js"],"component---src-pages-index-js":["styles.858d9e1bfd0c94d577d2.css","commons-bb84c67c674bddd9249e.js","component---src-pages-index-js-18bf280c969509fb1ec0.js"],"component---src-pages-page-2-js":["styles.858d9e1bfd0c94d577d2.css","commons-bb84c67c674bddd9249e.js","component---src-pages-page-2-js-894d927bbec8d66cc2ce.js"],"component---src-pages-using-typescript-tsx":["styles.858d9e1bfd0c94d577d2.css","commons-bb84c67c674bddd9249e.js","component---src-pages-using-typescript-tsx-5c68fcba212a517685e0.js"]},"childAssetsByChunkName":{}}